{
    "Symbol": "SAIC",
    "AssetType": "Common Stock",
    "Name": "Science Applications International Corporation Common Stock",
    "Description": "Science Applications International Corporation provides technical, engineering and business information technology (IT) services primarily in the United States. The company is headquartered in Reston, Virginia.",
    "CIK": "1571123",
    "Exchange": "NYSE",
    "Currency": "USD",
    "Country": "USA",
    "Sector": "TECHNOLOGY",
    "Industry": "SERVICES-COMPUTER INTEGRATED SYSTEMS DESIGN",
    "Address": "12010 SUNSET HILLS ROAD, RESTON, VA, US",
    "FiscalYearEnd": "January",
    "LatestQuarter": "2024-01-31",
    "MarketCapitalization": "6525259000",
    "EBITDA": "639000000",
    "PERatio": "14.23",
    "PEGRatio": "3.67",
    "BookValue": "34.33",
    "DividendPerShare": "1.48",
    "DividendYield": "0.0114",
    "EPS": "8.88",
    "RevenuePerShareTTM": "140.19",
    "ProfitMargin": "0.0641",
    "OperatingMarginTTM": "0.0455",
    "ReturnOnAssetsTTM": "0.0578",
    "ReturnOnEquityTTM": "0.273",
    "RevenueTTM": "7444000000",
    "GrossProfitTTM": "859000000",
    "DilutedEPSTTM": "8.88",
    "QuarterlyEarningsGrowthYOY": "-0.447",
    "QuarterlyRevenueGrowthYOY": "-0.117",
    "AnalystTargetPrice": "136.25",
    "AnalystRatingStrongBuy": "1",
    "AnalystRatingBuy": "1",
    "AnalystRatingHold": "8",
    "AnalystRatingSell": "1",
    "AnalystRatingStrongSell": "0",
    "TrailingPE": "14.23",
    "ForwardPE": "13.48",
    "PriceToSalesRatioTTM": "0.877",
    "PriceToBookRatio": "3.693",
    "EVToRevenue": "1.175",
    "EVToEBITDA": "9.91",
    "Beta": "0.702",
    "52WeekHigh": "145.17",
    "52WeekLow": "94.53",
    "50DayMovingAverage": "133.74",
    "200DayMovingAverage": "121.14",
    "SharesOutstanding": "51648000",
    "DividendDate": "2024-04-26",
    "ExDividendDate": "2024-04-11"
    }